README.rst
setup.py
Archippe.egg-info/PKG-INFO
Archippe.egg-info/SOURCES.txt
Archippe.egg-info/dependency_links.txt
Archippe.egg-info/entry_points.txt
Archippe.egg-info/requires.txt
Archippe.egg-info/top_level.txt
archippe/__init__.py
archippe/datapersistence.py
archippe/myinfluxdbclient.py
archippe/topic.py
archippe/schema/__init__.py
archippe/schema/influxdbclient.py
archippe/schema/schema.py
tests_unit/__init__.py
tests_unit/test_datapersistence.py
tests_unit/test_topic.py
tests_unit/test_validateconfig.py