Metadata-Version: 1.2
Name: Archippe
Version: 0.1.11
Summary: Archippe is a data persistence micro service for pelops. It uses influxdb to store incoming values and publishes the history a series upon request.
Home-page: https://gitlab.com/pelops/archippe/
Author: Tobias Gawron-Deutsch
Author-email: tobias@strix.at
License: MIT license
Keywords: mqtt influxdb persistence
Platform: UNKNOWN
Classifier: Development Status :: 4 - Beta
Classifier: Environment :: Console
Classifier: Environment :: No Input/Output (Daemon)
Classifier: Intended Audience :: Developers
Classifier: Programming Language :: Python :: 3
Classifier: Topic :: Utilities
Classifier: Topic :: Home Automation
Classifier: License :: OSI Approved :: MIT License
Requires-Python: >=3.5
